matrix.cpython-39-darwin.so
lanablas/__init__.py
lanablas-0.1.7.dist-info/LICENSE
lanablas-0.1.7.dist-info/METADATA
lanablas-0.1.7.dist-info/WHEEL
lanablas-0.1.7.dist-info/top_level.txt
lanablas-0.1.7.dist-info/RECORD
