Metadata-Version: 2.1
Name: lanablas
Version: 0.1.7
Summary: Extension module for matrix multiplication
Home-page: https://github.com/marcosalvalaggio/lana-blas
Author: Marco Salvalaggio
Author-email: mar.salvalaggio@gmail.com
License: MIT
Platform: UNKNOWN
Classifier: Programming Language :: Python :: 3
Classifier: License :: OSI Approved :: MIT License
Classifier: Operating System :: OS Independent
License-File: LICENSE
